{
    "classification": "hardware",
    "type": "bearing_16000_series",
    "size": "16021",
    "color": "",
    "description_main": "105_mm_id_160_mm_od_18_mm_depth",
    "description_extra": "",
    "manufacturer": "",
    "part_number": "",
    "from_yaml": false,
    "make_files": true,
    "filter": "bearing",
    "classification_upper": "HARDWARE",
    "classification_capital": "Hardware",
    "classification_first_letter": "h",
    "classification_first_letter_upper": "H",
    "type_upper": "BEARING_16000_SERIES",
    "type_capital": "Bearing 16000 Series",
    "type_first_letter": "b",
    "type_first_letter_upper": "B",
    "size_upper": "16021",
    "size_capital": "16021",
    "size_first_letter": "1",
    "size_first_letter_upper": "1",
    "color_upper": "",
    "color_capital": "",
    "color_first_letter": "",
    "color_first_letter_upper": "",
    "description_main_upper": "105_MM_ID_160_MM_OD_18_MM_DEPTH",
    "description_main_capital": "105 mm Id 160 mm Od 18 mm Depth",
    "description_main_first_letter": "1",
    "description_main_first_letter_upper": "1",
    "description_extra_upper": "",
    "description_extra_capital": "",
    "description_extra_first_letter": "",
    "description_extra_first_letter_upper": "",
    "manufacturer_upper": "",
    "manufacturer_capital": "",
    "manufacturer_first_letter": "",
    "manufacturer_first_letter_upper": "",
    "part_number_upper": "",
    "part_number_capital": "",
    "part_number_first_letter": "",
    "part_number_first_letter_upper": "",
    "id": "hardware_bearing_16000_series_16021_105_mm_id_160_mm_od_18_mm_depth",
    "id_no_class": "bearing_16000_series_16021_105_mm_id_160_mm_od_18_mm_depth",
    "id_no_type": "16021_105_mm_id_160_mm_od_18_mm_depth",
    "id_no_size": "105_mm_id_160_mm_od_18_mm_depth",
    "oomp_key": "oomp_hardware_bearing_16000_series_16021_105_mm_id_160_mm_od_18_mm_depth",
    "github_link": "https://github.com/oomlout/oomlout_oomp_part_src/tree/main/parts/hardware_bearing_16000_series_16021_105_mm_id_160_mm_od_18_mm_depth/working",
    "directory": "parts/hardware_bearing_16000_series_16021_105_mm_id_160_mm_od_18_mm_depth",
    "name": "Hardware Bearing 16000 Series 16021 105 Mm Id 160 Mm Od 18 Mm Depth",
    "name_no_class": "Bearing 16000 Series 16021 105 Mm Id 160 Mm Od 18 Mm Depth",
    "name_no_type": "16021 105 Mm Id 160 Mm Od 18 Mm Depth",
    "name_no_size": "105 Mm Id 160 Mm Od 18 Mm Depth",
    "short_code": "",
    "short_code_upper": "",
    "distributors": [],
    "manufacturers": [],
    "md5": "64f2f198c3f4e385b4cc3c078927c329",
    "md5_5": "64f2f",
    "md5_5_upper": "64F2F",
    "md5_6": "64f2f1",
    "md5_6_upper": "64F2F1",
    "md5_6_alpha": "3xss1",
    "md5_6_alpha_upper": "3XSS1",
    "md5_10": "64f2f198c3",
    "md5_10_upper": "64F2F198C3",
    "oomp_word": "sunflower one ticket",
    "oomp_word_list": [
        "sunflower",
        "one",
        "ticket"
    ],
    "oomp_word_emoji": ":sunflower: :one: :ticket:",
    "oomp_word_emoji_list": [
        ":sunflower:",
        ":one:",
        ":ticket:"
    ],
    "size_only_numbers": "16021",
    "size_only_numbers_no_zeros": "1621",
    "description_only_numbers": "10516018",
    "description_only_numbers_short": "1M",
    "name_no_size_short": "105 Mm Id 160 Mm Od 18 Mm Depth",
    "description_or_color": "1M",
    "description_or_color_upper": "1M",
    "markdown_full": "[hardware_bearing_16000_series_16021_105_mm_id_160_mm_od_18_mm_depth](https://github.com/oomlout/oomlout_oomp_part_src/tree/main/parts/hardware_bearing_16000_series_16021_105_mm_id_160_mm_od_18_mm_depth/working)<br>[](https://github.com/oomlout/oomlout_oomp_part_src/tree/main/parts/hardware_bearing_16000_series_16021_105_mm_id_160_mm_od_18_mm_depth/working)<br>[Hardware Bearing 16000 Series 16021 105 Mm Id 160 Mm Od 18 Mm Depth](https://github.com/oomlout/oomlout_oomp_part_src/tree/main/parts/hardware_bearing_16000_series_16021_105_mm_id_160_mm_od_18_mm_depth/working)<br><br>",
    "markdown_short": "[hardware_bearing_16000_series_16021_105_mm_id_160_mm_od_18_mm_depth](https://github.com/oomlout/oomlout_oomp_part_src/tree/main/parts/hardware_bearing_16000_series_16021_105_mm_id_160_mm_od_18_mm_depth/working)<br><br>"
}