{
    "classification": "hardware",
    "type": "bearing_600_series",
    "size": "628",
    "color": "",
    "description_main": "8_mm_id_24_mm_od_8_mm_depth",
    "description_extra": "",
    "manufacturer": "",
    "part_number": "",
    "from_yaml": false,
    "make_files": true,
    "filter": "bearing",
    "classification_upper": "HARDWARE",
    "classification_capital": "Hardware",
    "classification_first_letter": "h",
    "classification_first_letter_upper": "H",
    "type_upper": "BEARING_600_SERIES",
    "type_capital": "Bearing 600 Series",
    "type_first_letter": "b",
    "type_first_letter_upper": "B",
    "size_upper": "628",
    "size_capital": "628",
    "size_first_letter": "6",
    "size_first_letter_upper": "6",
    "color_upper": "",
    "color_capital": "",
    "color_first_letter": "",
    "color_first_letter_upper": "",
    "description_main_upper": "8_MM_ID_24_MM_OD_8_MM_DEPTH",
    "description_main_capital": "8 mm Id 24 mm Od 8 mm Depth",
    "description_main_first_letter": "8",
    "description_main_first_letter_upper": "8",
    "description_extra_upper": "",
    "description_extra_capital": "",
    "description_extra_first_letter": "",
    "description_extra_first_letter_upper": "",
    "manufacturer_upper": "",
    "manufacturer_capital": "",
    "manufacturer_first_letter": "",
    "manufacturer_first_letter_upper": "",
    "part_number_upper": "",
    "part_number_capital": "",
    "part_number_first_letter": "",
    "part_number_first_letter_upper": "",
    "id": "hardware_bearing_600_series_628_8_mm_id_24_mm_od_8_mm_depth",
    "id_no_class": "bearing_600_series_628_8_mm_id_24_mm_od_8_mm_depth",
    "id_no_type": "628_8_mm_id_24_mm_od_8_mm_depth",
    "id_no_size": "8_mm_id_24_mm_od_8_mm_depth",
    "oomp_key": "oomp_hardware_bearing_600_series_628_8_mm_id_24_mm_od_8_mm_depth",
    "github_link": "https://github.com/oomlout/oomlout_oomp_part_src/tree/main/parts/hardware_bearing_600_series_628_8_mm_id_24_mm_od_8_mm_depth/working",
    "directory": "parts/hardware_bearing_600_series_628_8_mm_id_24_mm_od_8_mm_depth",
    "name": "Hardware Bearing 600 Series 628 8 Mm Id 24 Mm Od 8 Mm Depth",
    "name_no_class": "Bearing 600 Series 628 8 Mm Id 24 Mm Od 8 Mm Depth",
    "name_no_type": "628 8 Mm Id 24 Mm Od 8 Mm Depth",
    "name_no_size": "8 Mm Id 24 Mm Od 8 Mm Depth",
    "short_code": "",
    "short_code_upper": "",
    "distributors": [],
    "manufacturers": [],
    "md5": "12a9a6ebf756ca64238abb2514820acf",
    "md5_5": "12a9a",
    "md5_5_upper": "12A9A",
    "md5_6": "12a9a6",
    "md5_6_upper": "12A9A6",
    "md5_6_alpha": "q7qe",
    "md5_6_alpha_upper": "Q7QE",
    "md5_10": "12a9a6ebf7",
    "md5_10_upper": "12A9A6EBF7",
    "oomp_word": "anger sandal trumpet",
    "oomp_word_list": [
        "anger",
        "sandal",
        "trumpet"
    ],
    "oomp_word_emoji": ":anger: :sandal: :trumpet:",
    "oomp_word_emoji_list": [
        ":anger:",
        ":sandal:",
        ":trumpet:"
    ],
    "size_only_numbers": "628",
    "size_only_numbers_no_zeros": "628",
    "description_only_numbers": "8248",
    "description_only_numbers_short": "8k2",
    "name_no_size_short": "8 Mm Id 24 Mm Od 8 Mm Depth",
    "description_or_color": "8k2",
    "description_or_color_upper": "8K2",
    "markdown_full": "[hardware_bearing_600_series_628_8_mm_id_24_mm_od_8_mm_depth](https://github.com/oomlout/oomlout_oomp_part_src/tree/main/parts/hardware_bearing_600_series_628_8_mm_id_24_mm_od_8_mm_depth/working)<br>[](https://github.com/oomlout/oomlout_oomp_part_src/tree/main/parts/hardware_bearing_600_series_628_8_mm_id_24_mm_od_8_mm_depth/working)<br>[Hardware Bearing 600 Series 628 8 Mm Id 24 Mm Od 8 Mm Depth](https://github.com/oomlout/oomlout_oomp_part_src/tree/main/parts/hardware_bearing_600_series_628_8_mm_id_24_mm_od_8_mm_depth/working)<br><br>",
    "markdown_short": "[hardware_bearing_600_series_628_8_mm_id_24_mm_od_8_mm_depth](https://github.com/oomlout/oomlout_oomp_part_src/tree/main/parts/hardware_bearing_600_series_628_8_mm_id_24_mm_od_8_mm_depth/working)<br><br>"
}